libbash.libs/libncursesw-71dc8801.so.6.4
libbash.libs/libintl-38a1e028.so.8.4.0
libbash/api.py
libbash/__init__.py
libbash/ctypes_bash_command.py
libbash/bash-5.2/pathnames.h.in
libbash/bash-5.2/mksyntax.c
libbash/bash-5.2/list.o
libbash/bash-5.2/assoc.o
libbash/bash-5.2/signames.h
libbash/bash-5.2/eval.c
libbash/bash-5.2/hashcmd.o
libbash/bash-5.2/redir.c
libbash/bash-5.2/.git
libbash/bash-5.2/mailcheck.c
libbash/bash-5.2/y.tab.c
libbash/bash-5.2/stringlib.o
libbash/bash-5.2/version.h
libbash/bash-5.2/alias.c
libbash/bash-5.2/print_cmd.c
libbash/bash-5.2/jobs.o
libbash/bash-5.2/hashlib.o
libbash/bash-5.2/arrayfunc.o
libbash/bash-5.2/dispose_cmd.c
libbash/bash-5.2/CHANGES
libbash/bash-5.2/findcmd.o
libbash/bash-5.2/dispose_cmd.h
libbash/bash-5.2/stamp-h
libbash/bash-5.2/bracecomp.c
libbash/bash-5.2/NOTES
libbash/bash-5.2/parser-built
libbash/bash-5.2/siglist.c
libbash/bash-5.2/findcmd.c
libbash/bash-5.2/nojobs.c
libbash/bash-5.2/make_cmd.c
libbash/bash-5.2/execute_cmd.o
libbash/bash-5.2/syntax.c
libbash/bash-5.2/NEWS
libbash/bash-5.2/parser.h
libbash/bash-5.2/xmalloc.o
libbash/bash-5.2/jobs.c
libbash/bash-5.2/subst.c
libbash/bash-5.2/make_cmd.h
libbash/bash-5.2/shell.c
libbash/bash-5.2/array.c
libbash/bash-5.2/bashhist.o
libbash/bash-5.2/hashlib.c
libbash/bash-5.2/hashcmd.c
libbash/bash-5.2/buildsignames.o
libbash/bash-5.2/lsignames.h
libbash/bash-5.2/execute_cmd.c
libbash/bash-5.2/bashhist.c
libbash/bash-5.2/config.status
libbash/bash-5.2/findcmd.h
libbash/bash-5.2/configure
libbash/bash-5.2/variables.o
libbash/bash-5.2/dispose_cmd.o
libbash/bash-5.2/error.c
libbash/bash-5.2/array.h
libbash/bash-5.2/bash.so
libbash/bash-5.2/error.o
libbash/bash-5.2/pathnames.h
libbash/bash-5.2/MANIFEST
libbash/bash-5.2/externs.h
libbash/bash-5.2/config-bot.h
libbash/bash-5.2/pathexp.h
libbash/bash-5.2/redir.o
libbash/bash-5.2/test.c
libbash/bash-5.2/ChangeLog
libbash/bash-5.2/assoc.h
libbash/bash-5.2/bashintl.h
libbash-0.1.13.dist-info/METADATA
libbash-0.1.13.dist-info/RECORD
libbash-0.1.13.dist-info/top_level.txt
libbash-0.1.13.dist-info/WHEEL
libbash-0.1.13.dist-info/LICENSE
