Metadata-Version: 2.1
Name: libbash
Version: 0.1.13
Summary: A library for parsing bash scripts.
Home-page: https://github.com/binpash/libbash/
Author: Seth Sabar
Author-email: Seth Sabar <sethsabar@gmail.com>
License: GPL-3.0
Project-URL: Homepage, https://github.com/binpash/libbash
Project-URL: Issues, https://github.com/binpash/libbash/issues
Classifier: Programming Language :: Python :: 3
Classifier: Operating System :: OS Independent
Requires-Python: >=3.8
License-File: LICENSE
